{
  "openapi": "3.0.3",
  "info": {
    "title": "Finance App Service API",
    "version": "1.0.0",
    "description": "OpenAPI documentation for all active routes in the finance-app-service-features project. Includes expected success responses, common error responses, and negative testing scenarios."
  },
  "servers": [
    {
      "url": "http://localhost:8080",
      "description": "Local development server"
    }
  ],
  "security": [
    {
      "BearerAuth": []
    }
  ],
  "components": {
    "securitySchemes": {
      "BearerAuth": {
        "type": "http",
        "scheme": "bearer",
        "bearerFormat": "JWT"
      }
    },
    "schemas": {
      "RequestIDMap": {
        "type": "object",
        "properties": {
          "request_id": {
            "type": "string",
            "example": "req-123e4567-e89b-12d3-a456-426614174000"
          }
        }
      },
      "ErrorResponse": {
        "type": "object",
        "properties": {
          "error": {
            "type": "string",
            "example": "Invalid request body"
          },
          "details": {
            "type": "string",
            "example": "Key: 'RegisterRequest.Email' Error:Field validation for 'Email' failed on the 'email' tag"
          },
          "request_id": {
            "type": "string",
            "example": "req-123e4567-e89b-12d3-a456-426614174000"
          }
        }
      },
      "HealthResponse": {
        "type": "object",
        "properties": {
          "status": {
            "type": "string",
            "example": "ok"
          },
          "timestamp": {
            "type": "string",
            "format": "date-time"
          }
        }
      },
      "ReadyResponse": {
        "type": "object",
        "properties": {
          "status": {
            "type": "string",
            "example": "ready"
          }
        }
      },
      "UserResponse": {
        "type": "object",
        "properties": {
          "id": {
            "type": "string",
            "example": "550e8400-e29b-41d4-a716-446655440000"
          },
          "username": {
            "type": "string",
            "example": "tubagus_aldi"
          },
          "email": {
            "type": "string",
            "example": "tubagus@example.com"
          },
          "created_at": {
            "type": "string",
            "format": "date-time",
            "example": "2025-01-01T15:00:00Z"
          }
        }
      },
      "RegisterRequest": {
        "type": "object",
        "required": [
          "username",
          "email",
          "password"
        ],
        "properties": {
          "username": {
            "type": "string",
            "example": "tubagus_aldi"
          },
          "email": {
            "type": "string",
            "format": "email",
            "example": "tubagus@example.com"
          },
          "password": {
            "type": "string",
            "format": "password",
            "example": "RahasiaNegara123!"
          }
        }
      },
      "RegisterResponse": {
        "type": "object",
        "properties": {
          "data": {
            "$ref": "#/components/schemas/UserResponse"
          },
          "request_id": {
            "type": "string",
            "example": "req-123e4567-e89b-12d3-a456-426614174000"
          }
        }
      },
      "LoginRequest": {
        "type": "object",
        "required": [
          "email",
          "password"
        ],
        "properties": {
          "email": {
            "type": "string",
            "format": "email",
            "example": "tubagus@example.com"
          },
          "password": {
            "type": "string",
            "format": "password",
            "example": "RahasiaNegara123!"
          }
        }
      },
      "LoginResponse": {
        "type": "object",
        "properties": {
          "data": {
            "type": "object",
            "properties": {
              "access_token": {
                "type": "string",
                "example": "eyJhbGciOiJIUzI1NiIsInR5cCI6IkpXVCJ9..."
              },
              "token_type": {
                "type": "string",
                "example": "Bearer"
              },
              "user": {
                "$ref": "#/components/schemas/UserResponse"
              }
            }
          },
          "request_id": {
            "type": "string",
            "example": "req-123e4567-e89b-12d3-a456-426614174000"
          }
        }
      },
      "ResetPasswordRequest": {
        "type": "object",
        "required": [
          "current_password",
          "new_password"
        ],
        "properties": {
          "current_password": {
            "type": "string",
            "format": "password",
            "example": "RahasiaNegara123!"
          },
          "new_password": {
            "type": "string",
            "format": "password",
            "example": "RahasiaNegara456!"
          }
        }
      },
      "ForgetPasswordRequest": {
        "type": "object",
        "required": [
          "email"
        ],
        "properties": {
          "email": {
            "type": "string",
            "format": "email",
            "example": "tubagus@example.com"
          }
        }
      },
      "ForgotPasswordResponse": {
        "type": "object",
        "properties": {
          "message": {
            "type": "string",
            "example": "Password reset link sent to your email"
          },
          "request_id": {
            "type": "string",
            "example": "req-123e4567-e89b-12d3-a456-426614174000"
          }
        }
      },
      "ResetPasswordWithTokenRequest": {
        "type": "object",
        "required": [
          "token",
          "new_password",
          "confirm_password"
        ],
        "properties": {
          "token": {
            "type": "string",
            "format": "uuid",
            "example": "550e8400-e29b-41d4-a716-446655440000"
          },
          "new_password": {
            "type": "string",
            "format": "password",
            "example": "RahasiaNegara456!"
          },
          "confirm_password": {
            "type": "string",
            "format": "password",
            "example": "RahasiaNegara456!"
          }
        }
      },
      "GenericMessageResponse": {
        "type": "object",
        "properties": {
          "message": {
            "type": "string",
            "example": "Password reset successful"
          },
          "request_id": {
            "type": "string",
            "example": "req-123e4567-e89b-12d3-a456-426614174000"
          }
        }
      },
      "Account": {
        "type": "object",
        "properties": {
          "id": {
            "type": "integer",
            "format": "int32",
            "example": 123
          },
          "user_id": {
            "type": "string",
            "example": "550e8400-e29b-41d4-a716-446655440000"
          },
          "account_name": {
            "type": "string",
            "example": "Personal Savings"
          },
          "description": {
            "type": "string",
            "example": "Primary savings account"
          },
          "balance": {
            "type": "number",
            "format": "double",
            "example": 2500.75
          },
          "created_at": {
            "type": "string",
            "format": "date-time",
            "example": "2025-10-01T10:00:00Z"
          }
        }
      },
      "CreateAccountRequest": {
        "type": "object",
        "required": [
          "account_name",
          "balance"
        ],
        "properties": {
          "account_name": {
            "type": "string",
            "example": "Personal Savings"
          },
          "description": {
            "type": "string",
            "example": "Primary savings account"
          },
          "balance": {
            "type": "number",
            "format": "double",
            "example": 2500.75
          }
        }
      },
      "CreateAccountResponse": {
        "type": "object",
        "properties": {
          "message": {
            "type": "string",
            "example": "Create account"
          },
          "data": {
            "type": "object",
            "properties": {
              "id": {
                "type": "integer",
                "format": "int32",
                "example": 123
              }
            }
          },
          "request_id": {
            "type": "string",
            "example": "req-123e4567-e89b-12d3-a456-426614174000"
          }
        }
      },
      "AccountListResponse": {
        "type": "object",
        "properties": {
          "message": {
            "type": "string",
            "example": "Get all accounts"
          },
          "data": {
            "type": "array",
            "items": {
              "$ref": "#/components/schemas/Account"
            }
          },
          "request_id": {
            "type": "string",
            "example": "req-123e4567-e89b-12d3-a456-426614174000"
          }
        }
      },
      "Transaction": {
        "type": "object",
        "properties": {
          "id": {
            "type": "integer",
            "format": "int32",
            "example": 345
          },
          "amount": {
            "type": "number",
            "format": "double",
            "example": 125.5
          },
          "transaction_type": {
            "type": "string",
            "example": "debit"
          },
          "description": {
            "type": "string",
            "example": "Office supplies"
          },
          "account_id": {
            "type": "string",
            "example": "550e8400-e29b-41d4-a716-446655440000"
          },
          "user_id": {
            "type": "string",
            "example": "550e8400-e29b-41d4-a716-446655440000"
          },
          "transaction_date": {
            "type": "string",
            "format": "date-time",
            "example": "2025-11-01T12:00:00Z"
          },
          "created_at": {
            "type": "string",
            "format": "date-time",
            "example": "2025-11-01T12:00:00Z"
          },
          "updated_at": {
            "type": "string",
            "format": "date-time",
            "example": "2025-11-01T12:00:00Z"
          }
        }
      },
      "CreateTransactionRequest": {
        "type": "object",
        "required": [
          "amount",
          "transaction_type",
          "account_id",
          "transaction_date"
        ],
        "properties": {
          "amount": {
            "type": "number",
            "format": "double",
            "example": 125.5
          },
          "transaction_type": {
            "type": "string",
            "example": "debit",
            "enum": [
              "debit",
              "credit"
            ]
          },
          "description": {
            "type": "string",
            "example": "Office supplies"
          },
          "account_id": {
            "type": "string",
            "format": "uuid",
            "example": "550e8400-e29b-41d4-a716-446655440000"
          },
          "transaction_date": {
            "type": "string",
            "format": "date-time",
            "example": "2025-11-01T12:00:00Z"
          }
        }
      },
      "UpdateTransactionRequest": {
        "type": "object",
        "properties": {
          "amount": {
            "type": "number",
            "format": "double",
            "example": 200.0
          },
          "transaction_type": {
            "type": "string",
            "example": "credit",
            "enum": [
              "debit",
              "credit"
            ]
          },
          "description": {
            "type": "string",
            "example": "Invoice payment"
          },
          "account_id": {
            "type": "string",
            "format": "uuid",
            "example": "550e8400-e29b-41d4-a716-446655440000"
          },
          "transaction_date": {
            "type": "string",
            "format": "date-time",
            "example": "2025-11-01T12:00:00Z"
          }
        }
      },
      "TransactionListResponse": {
        "type": "object",
        "properties": {
          "message": {
            "type": "string",
            "example": "Get all transactions"
          },
          "data": {
            "type": "array",
            "items": {
              "$ref": "#/components/schemas/Transaction"
            }
          },
          "request_id": {
            "type": "string",
            "example": "req-123e4567-e89b-12d3-a456-426614174000"
          }
        }
      },
      "TransactionDetailResponse": {
        "type": "object",
        "properties": {
          "message": {
            "type": "string",
            "example": "Get transaction by ID"
          },
          "data": {
            "$ref": "#/components/schemas/Transaction"
          },
          "request_id": {
            "type": "string",
            "example": "req-123e4567-e89b-12d3-a456-426614174000"
          }
        }
      },
      "Category": {
        "type": "object",
        "properties": {
          "id": {
            "type": "integer",
            "format": "int32",
            "example": 1
          },
          "name": {
            "type": "string",
            "example": "Food & Beverage"
          },
          "description": {
            "type": "string",
            "example": "Daily meals and drinks"
          },
          "created_at": {
            "type": "string",
            "format": "date-time",
            "example": "2026-05-24T10:00:00Z"
          }
        }
      },
      "CreateCategoryRequest": {
        "type": "object",
        "required": [
          "name"
        ],
        "properties": {
          "name": {
            "type": "string",
            "example": "Food & Beverage"
          },
          "description": {
            "type": "string",
            "example": "Daily meals and drinks"
          }
        }
      },
      "UpdateCategoryRequest": {
        "type": "object",
        "properties": {
          "name": {
            "type": "string",
            "example": "Transportation"
          },
          "description": {
            "type": "string",
            "example": "Fuel, toll, and parking"
          }
        }
      },
      "CreateCategoryResponse": {
        "type": "object",
        "properties": {
          "message": {
            "type": "string",
            "example": "Create category"
          },
          "data": {
            "type": "integer",
            "format": "int32",
            "example": 1
          },
          "request_id": {
            "type": "string",
            "example": "req-123e4567-e89b-12d3-a456-426614174000"
          }
        }
      },
      "CategoryListResponse": {
        "type": "object",
        "properties": {
          "message": {
            "type": "string",
            "example": "Get all categories"
          },
          "data": {
            "type": "array",
            "items": {
              "$ref": "#/components/schemas/Category"
            }
          }
        }
      },
      "CategoryDetailResponse": {
        "type": "object",
        "properties": {
          "message": {
            "type": "string",
            "example": "Get category by ID"
          },
          "data": {
            "$ref": "#/components/schemas/Category"
          }
        }
      }
    }
  },
  "paths": {
    "/ready": {
      "get": {
        "tags": [
          "System"
        ],
        "summary": "Readiness probe",
        "description": "Checks database readiness and returns service readiness status.",
        "security": [],
        "responses": {
          "200": {
            "description": "Service is ready.",
            "content": {
              "application/json": {
                "schema": {
                  "$ref": "#/components/schemas/ReadyResponse"
                }
              }
            }
          },
          "503": {
            "description": "Database not available.",
            "content": {
              "application/json": {
                "schema": {
                  "$ref": "#/components/schemas/ErrorResponse"
                },
                "example": {
                  "error": "database not available",
                  "request_id": "req-123e4567-e89b-12d3-a456-426614174000"
                }
              }
            }
          }
        },
        "x-negative-tests": [
          "Database connection unavailable returns 503 with error detail.",
          "Invalid method returns 405 if other HTTP verbs are used."
        ]
      }
    },
    "/health": {
      "get": {
        "tags": [
          "System"
        ],
        "summary": "Health check",
        "description": "Returns service health status without authentication.",
        "security": [],
        "responses": {
          "200": {
            "description": "Service is healthy.",
            "content": {
              "application/json": {
                "schema": {
                  "$ref": "#/components/schemas/HealthResponse"
                }
              }
            }
          }
        },
        "x-negative-tests": [
          "Not applicable for health endpoint because it does not accept a request body."
        ]
      }
    }
  }
}